setuptools_ziglang/__init__.py
setuptools_ziglang/build_zig_ext.py
setuptools_ziglang/zigcompiler.py
setuptools_ziglang/zigextension.py
setuptools_ziglang-0.0.4a0.dist-info/LICENSE
setuptools_ziglang-0.0.4a0.dist-info/METADATA
setuptools_ziglang-0.0.4a0.dist-info/WHEEL
setuptools_ziglang-0.0.4a0.dist-info/top_level.txt
setuptools_ziglang-0.0.4a0.dist-info/RECORD
