Metadata-Version: 2.1
Name: setuptools-ziglang
Version: 0.0.4a0
Summary: Setuptools extension for building Python extensions with the Zig compiler
Author-email: February Cozzocrea <february.cozzocrea@gmail.com>
License: MIT License
Project-URL: Repository, https://github.com/f-cozzocrea/setuptools-ziglang
Project-URL: Issues, https://github.com/f-cozzocrea/setuptools-ziglang/issues
Keywords: zig,ziglang,setuptools,extension
Classifier: License :: OSI Approved :: MIT License
Classifier: Development Status :: 3 - Alpha
Classifier: Intended Audience :: Developers
Classifier: Operating System :: OS Independent
Classifier: Programming Language :: Python :: 2.7
Classifier: Programming Language :: Python :: 3
Classifier: Programming Language :: Python :: 3.7
Classifier: Programming Language :: Python :: 3.8
Classifier: Programming Language :: Python :: 3.9
Classifier: Programming Language :: Python :: 3.10
Classifier: Programming Language :: Python :: 3.11
Classifier: Programming Language :: Python :: Implementation :: CPython
Classifier: Programming Language :: Python :: Implementation :: PyPy
Requires-Python: >=3.7
License-File: LICENSE
